senphora/__init__.py
senphora/exceptions.py
senphora/logger.py
senphora/drawer/__init__.py
senphora/drawer/cropper.py
senphora/drawer/draw_normal.py
senphora/drawer/find_normals.py
senphora/finder/__init__.py
senphora/finder/find_folders.py
senphora/image/__init__.py
senphora/image/cropper.py
senphora/image/format.py
senphora/image/jp2_png_converter.py
senphora/loader/__init__.py
senphora/loader/filter.py
senphora/loader/find_product.py
senphora/loader/load_data.py
senphora/loader/token_manager.py
senphora/polygon/__init__.py
senphora/polygon/polygon_functions.py
senphora/prepare/__init__.py
senphora/prepare/prepare_folder.py
senphora/utils/__init__.py
senphora/utils/date_functions.py
senphora/utils/exceptions.py
senphora/utils/find_folders.py
senphora/utils/jp2_png_converter.py
senphora/utils/logger.py
senphora/utils/split_on_blocks.py
senphora/utils/unzipper.py
senphora-0.2.0.0.dist-info/LICENSE
senphora-0.2.0.0.dist-info/METADATA
senphora-0.2.0.0.dist-info/WHEEL
senphora-0.2.0.0.dist-info/top_level.txt
senphora-0.2.0.0.dist-info/RECORD
